forgts/__init__.py
forgts/get_formatting.py
forgts/styling.py
forgts/translate_formatting.py
forgts-0.1.0.dist-info/LICENSE
forgts-0.1.0.dist-info/METADATA
forgts-0.1.0.dist-info/WHEEL
forgts-0.1.0.dist-info/top_level.txt
forgts-0.1.0.dist-info/RECORD
